anpe/__init__.py
anpe/cli.py
anpe/extractor.py
anpe/config/__init__.py
anpe/config/default.py
anpe/utils/__init__.py
anpe/utils/analyzer.py
anpe/utils/clean_models.py
anpe/utils/export.py
anpe/utils/model_finder.py
anpe/utils/setup_models.py
anpe-1.1.3.dist-info/METADATA
anpe-1.1.3.dist-info/WHEEL
anpe-1.1.3.dist-info/entry_points.txt
anpe-1.1.3.dist-info/licenses/LICENSE
anpe-1.1.3.dist-info/RECORD
