Metadata-Version: 2.4
Name: anpe
Version: 1.1.3
Summary: Accurately extract complete noun phrases with customisation and strctural output.
Project-URL: Homepage, https://github.com/rcverse/another-noun-phrase-extractor
Project-URL: Documentation, https://github.com/rcverse/another-noun-phrase-extractor
Project-URL: Bug Tracker, https://github.com/rcverse/another-noun-phrase-extractor/issues
Project-URL: Source Code, https://github.com/rcverse/another-noun-phrase-extractor
Author-email: Richard Chen <rcverse6@gmail.com>
License: MIT
License-File: LICENSE
Keywords: linguistics,natural language processing,nlp,noun phrase extraction,noun phrases,parsing,text processing
Classifier: Development Status :: 5 - Production/Stable
Classifier: Intended Audience :: Developers
Classifier: Intended Audience :: Science/Research
Classifier: License :: OSI Approved :: MIT License
Classifier: Natural Language :: English
Classifier: Operating System :: OS Independent
Classifier: Programming Language :: Python :: 3
Classifier: Programming Language :: Python :: 3.9
Classifier: Programming Language :: Python :: 3.10
Classifier: Programming Language :: Python :: 3.11
Classifier: Programming Language :: Python :: 3.12
Classifier: Topic :: Text Processing :: Linguistic
Requires-Python: <3.13,>=3.9
Requires-Dist: benepar>=0.2.0
Requires-Dist: nltk>=3.8.0
Requires-Dist: spacy>=3.5.0
